{
	"configurations" : 
	[
		{
			"directories" : 
			[
				{
					"build" : ".",
					"childIndexes" : 
					[
						1
					],
					"jsonFile" : "directory-.-Debug-f5ebdc15457944623624.json",
					"minimumCMakeVersion" : 
					{
						"string" : "3.20"
					},
					"projectIndex" : 0,
					"source" : ".",
					"targetIndexes" : 
					[
						0
					]
				},
				{
					"build" : "googletest/googletest",
					"jsonFile" : "directory-googletest.googletest-Debug-6c633108c67f9ce3c3c5.json",
					"minimumCMakeVersion" : 
					{
						"string" : "3.13"
					},
					"parentIndex" : 0,
					"projectIndex" : 1,
					"source" : "googletest/googletest",
					"targetIndexes" : 
					[
						1,
						2
					]
				}
			],
			"name" : "Debug",
			"projects" : 
			[
				{
					"childIndexes" : 
					[
						1
					],
					"directoryIndexes" : 
					[
						0
					],
					"name" : "Life",
					"targetIndexes" : 
					[
						0
					]
				},
				{
					"directoryIndexes" : 
					[
						1
					],
					"name" : "gtest",
					"parentIndex" : 0,
					"targetIndexes" : 
					[
						1,
						2
					]
				}
			],
			"targets" : 
			[
				{
					"directoryIndex" : 0,
					"id" : "Life::@6890427a1f51a3e7e1df",
					"jsonFile" : "target-Life-Debug-5748950aaaddfcce8251.json",
					"name" : "Life",
					"projectIndex" : 0
				},
				{
					"directoryIndex" : 1,
					"id" : "gtest::@f95b5c00bd49b3b4698d",
					"jsonFile" : "target-gtest-Debug-af01de2359a70a8d369c.json",
					"name" : "gtest",
					"projectIndex" : 1
				},
				{
					"directoryIndex" : 1,
					"id" : "gtest_main::@f95b5c00bd49b3b4698d",
					"jsonFile" : "target-gtest_main-Debug-bde72279c4b4146e6e20.json",
					"name" : "gtest_main",
					"projectIndex" : 1
				}
			]
		}
	],
	"kind" : "codemodel",
	"paths" : 
	{
		"build" : "/Users/thenemez/Desktop/proga/cpp_labs/Life/cmake-build-debug",
		"source" : "/Users/thenemez/Desktop/proga/cpp_labs/Life"
	},
	"version" : 
	{
		"major" : 2,
		"minor" : 5
	}
}
